x100daemon
