Metadata-Version: 1.1
Name: x100daemon
Version: 0.1.1
Summary: Make daemon for your program
Home-page: https://github.com/WayneZhouChina/x100daemon
Author: Wayne Zhou
Author-email: cumtxhzyy@gmail.com
License: MIT
Keywords: x100 daemon lite
Platform: UNKNOWN
Classifier: Development Status :: 4 - Beta
Classifier: Intended Audience :: Developers
Classifier: Topic :: Internet :: WWW/HTTP :: HTTP Servers
Classifier: License :: OSI Approved :: MIT License
Classifier: Programming Language :: Python :: 3.3
Classifier: Programming Language :: Python :: 3.4
Classifier: Programming Language :: Python :: 3 :: Only
